.gitignore
README.txt
bootstrap.py
buildout.cfg
setup.cfg
setup.py
docs/HISTORY.txt
docs/LICENSE.GPL
docs/LICENSE.txt
src/paula/__init__.py
src/paula.testing.egg-info/PKG-INFO
src/paula.testing.egg-info/SOURCES.txt
src/paula.testing.egg-info/dependency_links.txt
src/paula.testing.egg-info/entry_points.txt
src/paula.testing.egg-info/namespace_packages.txt
src/paula.testing.egg-info/not-zip-safe
src/paula.testing.egg-info/requires.txt
src/paula.testing.egg-info/top_level.txt
src/paula/testing/README.txt
src/paula/testing/__init__.py
src/paula/testing/config.py
src/paula/testing/configure.zcml
src/paula/testing/ftesting.zcml
src/paula/testing/interact.py
src/paula/testing/module.py
src/paula/testing/testing.py
src/paula/testing/tests.py
src/paula/testing/package/__init__.py
src/paula/testing/package/module.py
src/paula/testing/package/subpackage/__init__.py
src/paula/testing/package/subpackage/module.py