Metadata-Version: 1.0
Name: paula.testing
Version: 0.81
Summary: Paula testing framework
Home-page: https://chaoflow.net/projects/gsoc2008/z3membrane-ldap
Author: Florian Friesdorf
Author-email: flo@chaoflow.net
License: AGPL
Platform: UNKNOWN
Classifier: Development Status :: 2 - Pre-Alpha
Classifier: Environment :: Web Environment
Classifier: Intended Audience :: Developers
Classifier: Programming Language :: Python
Classifier: Natural Language :: English
Classifier: Operating System :: OS Independent
Classifier: Topic :: Internet :: WWW/HTTP
Classifier: Framework :: Zope3
